autoiperf3/__init__.py
autoiperf3/__main__.py
autoiperf3/config.py
autoiperf3-0.1.2.dist-info/DESCRIPTION.rst
autoiperf3-0.1.2.dist-info/METADATA
autoiperf3-0.1.2.dist-info/RECORD
autoiperf3-0.1.2.dist-info/WHEEL
autoiperf3-0.1.2.dist-info/entry_points.txt
autoiperf3-0.1.2.dist-info/metadata.json
autoiperf3-0.1.2.dist-info/top_level.txt
